drf_custom_related_field/__init__.py
drf_custom_related_field/fields.py
drf_custom_related_field-0.2.dist-info/LICENSE
drf_custom_related_field-0.2.dist-info/METADATA
drf_custom_related_field-0.2.dist-info/WHEEL
drf_custom_related_field-0.2.dist-info/top_level.txt
drf_custom_related_field-0.2.dist-info/RECORD
