Metadata-Version: 2.1
Name: drf-custom-related-field
Version: 0.2
Summary: Custom relation field for django-rest-framework's serializers
Home-page: https://github.com/ckkz-it/drf-custom-related-field
Author: Andrey Laguta
Author-email: cirkus.kz@gmail.com
License: MIT
Keywords: drf restframework rest_framework django_rest_framework serializers drf_custom_related_field
Platform: UNKNOWN
Classifier: Development Status :: 4 - Beta
Classifier: Environment :: Web Environment
Classifier: Framework :: Django
Classifier: Framework :: Django :: 2.0
Classifier: Framework :: Django :: 2.1
Classifier: Framework :: Django :: 2.2
Classifier: Framework :: Django :: 3.0
Classifier: Intended Audience :: Developers
Classifier: Operating System :: OS Independent
Classifier: Programming Language :: Python :: 3.5
Classifier: Programming Language :: Python :: 3.6
Classifier: Programming Language :: Python :: 3.7
Classifier: Topic :: Internet :: WWW/HTTP
Requires-Dist: django (>=2.0)
Requires-Dist: djangorestframework (>=3.0)
